[{"model": "admin.logentry", "pk": 1, "fields": {"action_time": "2025-10-01T15:45:16.521Z", "user": 1, "content_type": 7, "object_id": "1", "object_repr": "Python", "action_flag": 1, "change_message": "[{\"added\": {}}]"}}, {"model": "admin.logentry", "pk": 2, "fields": {"action_time": "2025-11-12T13:21:18.843Z", "user": 1, "content_type": 8, "object_id": "1", "object_repr": "Основы Django", "action_flag": 1, "change_message": "[{\"added\": {}}]"}}, {"model": "admin.logentry", "pk": 3, "fields": {"action_time": "2025-11-12T13:21:31.192Z", "user": 1, "content_type": 8, "object_id": "2", "object_repr": "Первое приложение", "action_flag": 1, "change_message": "[{\"added\": {}}]"}}, {"model": "admin.logentry", "pk": 4, "fields": {"action_time": "2025-11-12T13:21:43.611Z", "user": 1, "content_type": 8, "object_id": "3", "object_repr": "Шаблоны и контекст", "action_flag": 1, "change_message": "[{\"added\": {}}]"}}, {"model": "admin.logentry", "pk": 5, "fields": {"action_time": "2025-11-12T13:46:28.507Z", "user": 1, "content_type": 9, "object_id": "1", "object_repr": "Введение в Python", "action_flag": 1, "change_message": "[{\"added\": {}}]"}}, {"model": "admin.logentry", "pk": 6, "fields": {"action_time": "2025-11-12T13:46:37.677Z", "user": 1, "content_type": 9, "object_id": "2", "object_repr": "Переменные и типы данных", "action_flag": 1, "change_message": "[{\"added\": {}}]"}}, {"model": "admin.logentry", "pk": 7, "fields": {"action_time": "2025-11-12T13:46:46.463Z", "user": 1, "content_type": 9, "object_id": "3", "object_repr": "Условия и циклы", "action_flag": 1, "change_message": "[{\"added\": {}}]"}}, {"model": "admin.logentry", "pk": 8, "fields": {"action_time": "2025-11-12T13:46:56.273Z", "user": 1, "content_type": 9, "object_id": "4", "object_repr": "Функции и аргументы", "action_flag": 1, "change_message": "[{\"added\": {}}]"}}, {"model": "admin.logentry", "pk": 9, "fields": {"action_time": "2025-11-12T18:01:48.294Z", "user": 1, "content_type": 10, "object_id": "1", "object_repr": "Теория", "action_flag": 1, "change_message": "[{\"added\": {}}]"}}, {"model": "admin.logentry", "pk": 10, "fields": {"action_time": "2025-11-12T19:31:32.903Z", "user": 1, "content_type": 10, "object_id": "1", "object_repr": "Теория", "action_flag": 2, "change_message": "[{\"changed\": {\"fields\": [\"\\u041f\\u043e\\u0440\\u044f\\u0434\\u043e\\u043a\"]}}]"}}, {"model": "admin.logentry", "pk": 11, "fields": {"action_time": "2025-11-12T20:46:55.271Z", "user": 1, "content_type": 10, "object_id": "1", "object_repr": "Теория", "action_flag": 2, "change_message": "[{\"changed\": {\"fields\": [\"\\u041a\\u043e\\u043d\\u0442\\u0435\\u043d\\u0442 \\u0441\\u0442\\u043e\\u0440\\u0456\\u043d\\u043a\\u0438\"]}}]"}}, {"model": "admin.logentry", "pk": 12, "fields": {"action_time": "2025-11-12T21:07:35.953Z", "user": 1, "content_type": 10, "object_id": "1", "object_repr": "Теория", "action_flag": 2, "change_message": "[{\"changed\": {\"fields\": [\"\\u041a\\u043e\\u043d\\u0442\\u0435\\u043d\\u0442 \\u0441\\u0442\\u043e\\u0440\\u0456\\u043d\\u043a\\u0438\"]}}]"}}, {"model": "admin.logentry", "pk": 13, "fields": {"action_time": "2025-11-18T06:56:35.215Z", "user": 1, "content_type": 10, "object_id": "1", "object_repr": "Теория", "action_flag": 2, "change_message": "[{\"changed\": {\"fields\": [\"\\u041a\\u043e\\u043d\\u0442\\u0435\\u043d\\u0442 \\u0441\\u0442\\u043e\\u0440\\u0456\\u043d\\u043a\\u0438\"]}}]"}}, {"model": "admin.logentry", "pk": 14, "fields": {"action_time": "2025-11-18T07:16:12.311Z", "user": 1, "content_type": 10, "object_id": "1", "object_repr": "Теория", "action_flag": 2, "change_message": "[{\"changed\": {\"fields\": [\"\\u041a\\u043e\\u043d\\u0442\\u0435\\u043d\\u0442 \\u0441\\u0442\\u043e\\u0440\\u0456\\u043d\\u043a\\u0438\"]}}]"}}, {"model": "admin.logentry", "pk": 15, "fields": {"action_time": "2025-11-18T07:17:11.157Z", "user": 1, "content_type": 10, "object_id": "1", "object_repr": "Теория", "action_flag": 2, "change_message": "[{\"changed\": {\"fields\": [\"\\u041a\\u043e\\u043d\\u0442\\u0435\\u043d\\u0442 \\u0441\\u0442\\u043e\\u0440\\u0456\\u043d\\u043a\\u0438\"]}}]"}}, {"model": "admin.logentry", "pk": 16, "fields": {"action_time": "2025-11-18T07:48:20.938Z", "user": 1, "content_type": 10, "object_id": "1", "object_repr": "Теория", "action_flag": 2, "change_message": "[{\"changed\": {\"fields\": [\"Markdown description\"]}}]"}}, {"model": "admin.logentry", "pk": 17, "fields": {"action_time": "2025-11-18T20:02:15.048Z", "user": 1, "content_type": 9, "object_id": "3", "object_repr": "Условия и циклы", "action_flag": 2, "change_message": "[{\"changed\": {\"fields\": [\"Content\"]}}]"}}, {"model": "admin.logentry", "pk": 18, "fields": {"action_time": "2025-11-18T20:36:02.726Z", "user": 1, "content_type": 9, "object_id": "2", "object_repr": "Переменные и типы данных", "action_flag": 2, "change_message": "[{\"changed\": {\"fields\": [\"Content\"]}}]"}}, {"model": "admin.logentry", "pk": 19, "fields": {"action_time": "2025-11-18T20:48:40.758Z", "user": 1, "content_type": 9, "object_id": "2", "object_repr": "Переменные и типы данных", "action_flag": 2, "change_message": "[]"}}, {"model": "admin.logentry", "pk": 20, "fields": {"action_time": "2025-11-19T04:40:55.155Z", "user": 1, "content_type": 9, "object_id": "3", "object_repr": "Условия и циклы", "action_flag": 2, "change_message": "[{\"changed\": {\"fields\": [\"Content\"]}}]"}}, {"model": "admin.logentry", "pk": 21, "fields": {"action_time": "2025-11-19T05:06:58.966Z", "user": 1, "content_type": 9, "object_id": "2", "object_repr": "Переменные и типы данных", "action_flag": 2, "change_message": "[]"}}, {"model": "admin.logentry", "pk": 22, "fields": {"action_time": "2025-11-19T05:10:07.114Z", "user": 1, "content_type": 9, "object_id": "4", "object_repr": "Функции и аргументы", "action_flag": 2, "change_message": "[{\"changed\": {\"fields\": [\"Content\"]}}]"}}, {"model": "admin.logentry", "pk": 23, "fields": {"action_time": "2025-11-19T05:39:47.138Z", "user": 1, "content_type": 9, "object_id": "4", "object_repr": "Функции и аргументы", "action_flag": 2, "change_message": "[{\"changed\": {\"fields\": [\"Content\"]}}]"}}, {"model": "admin.logentry", "pk": 24, "fields": {"action_time": "2025-11-19T05:41:42.172Z", "user": 1, "content_type": 9, "object_id": "4", "object_repr": "Функции и аргументы", "action_flag": 2, "change_message": "[{\"changed\": {\"fields\": [\"Content\"]}}]"}}, {"model": "admin.logentry", "pk": 25, "fields": {"action_time": "2025-11-19T05:50:40.657Z", "user": 1, "content_type": 9, "object_id": "4", "object_repr": "Функции и аргументы", "action_flag": 2, "change_message": "[{\"changed\": {\"fields\": [\"Content\"]}}]"}}, {"model": "admin.logentry", "pk": 26, "fields": {"action_time": "2025-11-19T05:56:28.331Z", "user": 1, "content_type": 9, "object_id": "4", "object_repr": "Функции и аргументы", "action_flag": 2, "change_message": "[{\"changed\": {\"fields\": [\"Content\"]}}]"}}, {"model": "admin.logentry", "pk": 27, "fields": {"action_time": "2025-11-19T06:14:47.315Z", "user": 1, "content_type": 9, "object_id": "1", "object_repr": "Введение в Python", "action_flag": 2, "change_message": "[{\"changed\": {\"fields\": [\"Content\"]}}]"}}, {"model": "admin.logentry", "pk": 28, "fields": {"action_time": "2025-11-20T19:39:48.668Z", "user": 1, "content_type": 9, "object_id": "1", "object_repr": "Введение в Python", "action_flag": 2, "change_message": "[{\"changed\": {\"fields\": [\"Content\"]}}]"}}, {"model": "admin.logentry", "pk": 29, "fields": {"action_time": "2025-11-21T12:04:00.878Z", "user": 1, "content_type": 9, "object_id": "4", "object_repr": "Функции и аргументы", "action_flag": 2, "change_message": "[{\"changed\": {\"fields\": [\"Content\"]}}]"}}, {"model": "admin.logentry", "pk": 30, "fields": {"action_time": "2025-11-21T12:05:08.493Z", "user": 1, "content_type": 9, "object_id": "4", "object_repr": "Функции и аргументы", "action_flag": 2, "change_message": "[{\"changed\": {\"fields\": [\"Content\"]}}]"}}, {"model": "admin.logentry", "pk": 31, "fields": {"action_time": "2025-11-21T12:06:13.446Z", "user": 1, "content_type": 9, "object_id": "4", "object_repr": "Функции и аргументы", "action_flag": 2, "change_message": "[{\"changed\": {\"fields\": [\"Content\"]}}]"}}, {"model": "admin.logentry", "pk": 32, "fields": {"action_time": "2025-11-21T12:06:57.856Z", "user": 1, "content_type": 9, "object_id": "4", "object_repr": "Функции и аргументы", "action_flag": 2, "change_message": "[{\"changed\": {\"fields\": [\"Content\"]}}]"}}, {"model": "admin.logentry", "pk": 33, "fields": {"action_time": "2025-11-21T12:07:10.645Z", "user": 1, "content_type": 9, "object_id": "4", "object_repr": "Функции и аргументы", "action_flag": 2, "change_message": "[{\"changed\": {\"fields\": [\"Content\"]}}]"}}, {"model": "admin.logentry", "pk": 34, "fields": {"action_time": "2025-11-21T12:07:34.356Z", "user": 1, "content_type": 9, "object_id": "4", "object_repr": "Функции и аргументы", "action_flag": 2, "change_message": "[{\"changed\": {\"fields\": [\"Content\"]}}]"}}, {"model": "admin.logentry", "pk": 35, "fields": {"action_time": "2025-11-21T12:08:09.630Z", "user": 1, "content_type": 9, "object_id": "4", "object_repr": "Функции и аргументы", "action_flag": 2, "change_message": "[{\"changed\": {\"fields\": [\"Content\"]}}]"}}, {"model": "admin.logentry", "pk": 36, "fields": {"action_time": "2025-11-21T13:08:17.621Z", "user": 1, "content_type": 9, "object_id": "4", "object_repr": "Функции и аргументы", "action_flag": 2, "change_message": "[{\"changed\": {\"fields\": [\"Content\"]}}]"}}, {"model": "admin.logentry", "pk": 37, "fields": {"action_time": "2025-11-21T13:33:07.898Z", "user": 1, "content_type": 9, "object_id": "1", "object_repr": "Введение в Python", "action_flag": 2, "change_message": "[{\"changed\": {\"fields\": [\"Content\"]}}]"}}, {"model": "admin.logentry", "pk": 38, "fields": {"action_time": "2025-11-21T13:33:53.525Z", "user": 1, "content_type": 9, "object_id": "1", "object_repr": "Введение в Python", "action_flag": 2, "change_message": "[{\"changed\": {\"fields\": [\"Content\"]}}]"}}, {"model": "admin.logentry", "pk": 39, "fields": {"action_time": "2025-11-21T13:51:46.139Z", "user": 1, "content_type": 9, "object_id": "1", "object_repr": "Введение в Python", "action_flag": 2, "change_message": "[{\"changed\": {\"fields\": [\"\\u041f\\u043e\\u0440\\u044f\\u0434\\u043e\\u043a\"]}}]"}}, {"model": "admin.logentry", "pk": 40, "fields": {"action_time": "2025-11-21T13:51:54.230Z", "user": 1, "content_type": 9, "object_id": "2", "object_repr": "Переменные и типы данных", "action_flag": 2, "change_message": "[{\"changed\": {\"fields\": [\"\\u041f\\u043e\\u0440\\u044f\\u0434\\u043e\\u043a\"]}}]"}}, {"model": "admin.logentry", "pk": 41, "fields": {"action_time": "2025-11-21T13:51:59.733Z", "user": 1, "content_type": 9, "object_id": "3", "object_repr": "Условия и циклы", "action_flag": 2, "change_message": "[{\"changed\": {\"fields\": [\"\\u041f\\u043e\\u0440\\u044f\\u0434\\u043e\\u043a\"]}}]"}}, {"model": "admin.logentry", "pk": 42, "fields": {"action_time": "2025-11-21T13:52:04.557Z", "user": 1, "content_type": 9, "object_id": "4", "object_repr": "Функции и аргументы", "action_flag": 2, "change_message": "[{\"changed\": {\"fields\": [\"\\u041f\\u043e\\u0440\\u044f\\u0434\\u043e\\u043a\"]}}]"}}, {"model": "admin.logentry", "pk": 43, "fields": {"action_time": "2025-11-21T13:52:11.904Z", "user": 1, "content_type": 8, "object_id": "1", "object_repr": "Основы Django", "action_flag": 2, "change_message": "[{\"changed\": {\"fields\": [\"\\u041f\\u043e\\u0440\\u044f\\u0434\\u043e\\u043a\"]}}]"}}, {"model": "admin.logentry", "pk": 44, "fields": {"action_time": "2025-11-21T13:52:18.803Z", "user": 1, "content_type": 8, "object_id": "2", "object_repr": "Первое приложение", "action_flag": 2, "change_message": "[{\"changed\": {\"fields\": [\"\\u041f\\u043e\\u0440\\u044f\\u0434\\u043e\\u043a\"]}}]"}}, {"model": "admin.logentry", "pk": 45, "fields": {"action_time": "2025-11-21T13:52:48.908Z", "user": 1, "content_type": 8, "object_id": "3", "object_repr": "Шаблоны и контекст", "action_flag": 2, "change_message": "[{\"changed\": {\"fields\": [\"\\u041f\\u043e\\u0440\\u044f\\u0434\\u043e\\u043a\"]}}]"}}, {"model": "admin.logentry", "pk": 46, "fields": {"action_time": "2025-11-21T13:53:54.627Z", "user": 1, "content_type": 9, "object_id": "3", "object_repr": "Условия и циклы", "action_flag": 2, "change_message": "[{\"changed\": {\"fields\": [\"\\u041f\\u043e\\u0440\\u044f\\u0434\\u043e\\u043a\"]}}]"}}, {"model": "admin.logentry", "pk": 47, "fields": {"action_time": "2025-11-21T14:44:11.876Z", "user": 1, "content_type": 9, "object_id": "5", "object_repr": "Вторая норм лекция", "action_flag": 1, "change_message": "[{\"added\": {}}]"}}, {"model": "admin.logentry", "pk": 48, "fields": {"action_time": "2025-11-21T14:44:41.539Z", "user": 1, "content_type": 9, "object_id": "5", "object_repr": "Вторая норм лекция", "action_flag": 2, "change_message": "[{\"changed\": {\"fields\": [\"Content\"]}}]"}}, {"model": "admin.logentry", "pk": 49, "fields": {"action_time": "2025-11-21T14:44:52.286Z", "user": 1, "content_type": 9, "object_id": "5", "object_repr": "Вторая норм лекция", "action_flag": 2, "change_message": "[{\"changed\": {\"fields\": [\"Content\"]}}]"}}, {"model": "admin.logentry", "pk": 50, "fields": {"action_time": "2025-11-21T14:45:19.368Z", "user": 1, "content_type": 9, "object_id": "5", "object_repr": "Вторая норм лекция", "action_flag": 2, "change_message": "[{\"changed\": {\"fields\": [\"Content\"]}}]"}}, {"model": "admin.logentry", "pk": 51, "fields": {"action_time": "2025-11-22T05:29:08.222Z", "user": 1, "content_type": 12, "object_id": "1", "object_repr": "Note object (1)", "action_flag": 1, "change_message": "[{\"added\": {}}]"}}, {"model": "admin.logentry", "pk": 52, "fields": {"action_time": "2025-11-22T06:00:08.131Z", "user": 1, "content_type": 9, "object_id": "4", "object_repr": "Функции и аргументы", "action_flag": 2, "change_message": "[{\"changed\": {\"fields\": [\"Content\"]}}]"}}, {"model": "admin.logentry", "pk": 53, "fields": {"action_time": "2025-11-25T06:44:33.347Z", "user": 1, "content_type": 9, "object_id": "3", "object_repr": "Добавление и удаление столбцов в таблице", "action_flag": 2, "change_message": "[{\"changed\": {\"fields\": [\"\\u041d\\u0430\\u0437\\u0432\\u0430 \\u0442\\u0435\\u043c\\u0438\", \"\\u0421\\u043b\\u0430\\u0433\", \"Content\", \"\\u041f\\u043e\\u0440\\u044f\\u0434\\u043e\\u043a\"]}}]"}}, {"model": "auth.permission", "pk": 1, "fields": {"name": "Can add log entry", "content_type": 1, "codename": "add_logentry"}}, {"model": "auth.permission", "pk": 2, "fields": {"name": "Can change log entry", "content_type": 1, "codename": "change_logentry"}}, {"model": "auth.permission", "pk": 3, "fields": {"name": "Can delete log entry", "content_type": 1, "codename": "delete_logentry"}}, {"model": "auth.permission", "pk": 4, "fields": {"name": "Can view log entry", "content_type": 1, "codename": "view_logentry"}}, {"model": "auth.permission", "pk": 5, "fields": {"name": "Can add permission", "content_type": 2, "codename": "add_permission"}}, {"model": "auth.permission", "pk": 6, "fields": {"name": "Can change permission", "content_type": 2, "codename": "change_permission"}}, {"model": "auth.permission", "pk": 7, "fields": {"name": "Can delete permission", "content_type": 2, "codename": "delete_permission"}}, {"model": "auth.permission", "pk": 8, "fields": {"name": "Can view permission", "content_type": 2, "codename": "view_permission"}}, {"model": "auth.permission", "pk": 9, "fields": {"name": "Can add group", "content_type": 3, "codename": "add_group"}}, {"model": "auth.permission", "pk": 10, "fields": {"name": "Can change group", "content_type": 3, "codename": "change_group"}}, {"model": "auth.permission", "pk": 11, "fields": {"name": "Can delete group", "content_type": 3, "codename": "delete_group"}}, {"model": "auth.permission", "pk": 12, "fields": {"name": "Can view group", "content_type": 3, "codename": "view_group"}}, {"model": "auth.permission", "pk": 13, "fields": {"name": "Can add user", "content_type": 4, "codename": "add_user"}}, {"model": "auth.permission", "pk": 14, "fields": {"name": "Can change user", "content_type": 4, "codename": "change_user"}}, {"model": "auth.permission", "pk": 15, "fields": {"name": "Can delete user", "content_type": 4, "codename": "delete_user"}}, {"model": "auth.permission", "pk": 16, "fields": {"name": "Can view user", "content_type": 4, "codename": "view_user"}}, {"model": "auth.permission", "pk": 17, "fields": {"name": "Can add content type", "content_type": 5, "codename": "add_contenttype"}}, {"model": "auth.permission", "pk": 18, "fields": {"name": "Can change content type", "content_type": 5, "codename": "change_contenttype"}}, {"model": "auth.permission", "pk": 19, "fields": {"name": "Can delete content type", "content_type": 5, "codename": "delete_contenttype"}}, {"model": "auth.permission", "pk": 20, "fields": {"name": "Can view content type", "content_type": 5, "codename": "view_contenttype"}}, {"model": "auth.permission", "pk": 21, "fields": {"name": "Can add session", "content_type": 6, "codename": "add_session"}}, {"model": "auth.permission", "pk": 22, "fields": {"name": "Can change session", "content_type": 6, "codename": "change_session"}}, {"model": "auth.permission", "pk": 23, "fields": {"name": "Can delete session", "content_type": 6, "codename": "delete_session"}}, {"model": "auth.permission", "pk": 24, "fields": {"name": "Can view session", "content_type": 6, "codename": "view_session"}}, {"model": "auth.permission", "pk": 25, "fields": {"name": "Can add course", "content_type": 7, "codename": "add_course"}}, {"model": "auth.permission", "pk": 26, "fields": {"name": "Can change course", "content_type": 7, "codename": "change_course"}}, {"model": "auth.permission", "pk": 27, "fields": {"name": "Can delete course", "content_type": 7, "codename": "delete_course"}}, {"model": "auth.permission", "pk": 28, "fields": {"name": "Can view course", "content_type": 7, "codename": "view_course"}}, {"model": "auth.permission", "pk": 29, "fields": {"name": "Can add module", "content_type": 8, "codename": "add_module"}}, {"model": "auth.permission", "pk": 30, "fields": {"name": "Can change module", "content_type": 8, "codename": "change_module"}}, {"model": "auth.permission", "pk": 31, "fields": {"name": "Can delete module", "content_type": 8, "codename": "delete_module"}}, {"model": "auth.permission", "pk": 32, "fields": {"name": "Can view module", "content_type": 8, "codename": "view_module"}}, {"model": "auth.permission", "pk": 33, "fields": {"name": "Can add lesson", "content_type": 9, "codename": "add_lesson"}}, {"model": "auth.permission", "pk": 34, "fields": {"name": "Can change lesson", "content_type": 9, "codename": "change_lesson"}}, {"model": "auth.permission", "pk": 35, "fields": {"name": "Can delete lesson", "content_type": 9, "codename": "delete_lesson"}}, {"model": "auth.permission", "pk": 36, "fields": {"name": "Can view lesson", "content_type": 9, "codename": "view_lesson"}}, {"model": "auth.permission", "pk": 37, "fields": {"name": "Can add step", "content_type": 10, "codename": "add_step"}}, {"model": "auth.permission", "pk": 38, "fields": {"name": "Can change step", "content_type": 10, "codename": "change_step"}}, {"model": "auth.permission", "pk": 39, "fields": {"name": "Can delete step", "content_type": 10, "codename": "delete_step"}}, {"model": "auth.permission", "pk": 40, "fields": {"name": "Can view step", "content_type": 10, "codename": "view_step"}}, {"model": "auth.permission", "pk": 41, "fields": {"name": "Can add Прогрес лекції", "content_type": 11, "codename": "add_lessonprogress"}}, {"model": "auth.permission", "pk": 42, "fields": {"name": "Can change Прогрес лекції", "content_type": 11, "codename": "change_lessonprogress"}}, {"model": "auth.permission", "pk": 43, "fields": {"name": "Can delete Прогрес лекції", "content_type": 11, "codename": "delete_lessonprogress"}}, {"model": "auth.permission", "pk": 44, "fields": {"name": "Can view Прогрес лекції", "content_type": 11, "codename": "view_lessonprogress"}}, {"model": "auth.permission", "pk": 45, "fields": {"name": "Can add note", "content_type": 12, "codename": "add_note"}}, {"model": "auth.permission", "pk": 46, "fields": {"name": "Can change note", "content_type": 12, "codename": "change_note"}}, {"model": "auth.permission", "pk": 47, "fields": {"name": "Can delete note", "content_type": 12, "codename": "delete_note"}}, {"model": "auth.permission", "pk": 48, "fields": {"name": "Can view note", "content_type": 12, "codename": "view_note"}}, {"model": "auth.user", "pk": 1, "fields": {"password": "pbkdf2_sha256$1000000$8evkyBROfQa6SLQtmZ4KbZ$HuRPo4uIMB0kqnw5DdeRjJICQEfasahw7wKv+dWi8pw=", "last_login": "2025-11-25T06:40:03.935Z", "is_superuser": true, "username": "igor", "first_name": "", "last_name": "", "email": "", "is_staff": true, "is_active": true, "date_joined": "2025-10-01T15:36:56.805Z", "groups": [], "user_permissions": []}}, {"model": "contenttypes.contenttype", "pk": 1, "fields": {"app_label": "admin", "model": "logentry"}}, {"model": "contenttypes.contenttype", "pk": 2, "fields": {"app_label": "auth", "model": "permission"}}, {"model": "contenttypes.contenttype", "pk": 3, "fields": {"app_label": "auth", "model": "group"}}, {"model": "contenttypes.contenttype", "pk": 4, "fields": {"app_label": "auth", "model": "user"}}, {"model": "contenttypes.contenttype", "pk": 5, "fields": {"app_label": "contenttypes", "model": "contenttype"}}, {"model": "contenttypes.contenttype", "pk": 6, "fields": {"app_label": "sessions", "model": "session"}}, {"model": "contenttypes.contenttype", "pk": 7, "fields": {"app_label": "courses", "model": "course"}}, {"model": "contenttypes.contenttype", "pk": 8, "fields": {"app_label": "courses", "model": "module"}}, {"model": "contenttypes.contenttype", "pk": 9, "fields": {"app_label": "courses", "model": "lesson"}}, {"model": "contenttypes.contenttype", "pk": 10, "fields": {"app_label": "courses", "model": "step"}}, {"model": "contenttypes.contenttype", "pk": 11, "fields": {"app_label": "courses", "model": "lessonprogress"}}, {"model": "contenttypes.contenttype", "pk": 12, "fields": {"app_label": "courses", "model": "note"}}, {"model": "sessions.session", "pk": "0avl7haqo8u22kixzvumop345whaayvy", "fields": {"session_data": ".eJxVjDsOwjAQBe_iGll2PnZMSc8Zot19Ng4gW8qnQtwdIqWA9s3Me6mRtjWP2xLncYI6K6tOvxuTPGLZAe5UblVLLes8sd4VfdBFXyvi83K4fweZlvytUxMZgZBM0_ngQH3yxiUIhFrvbIeBRSzQBxhKcMENzNL6zjWM1qr3BxzQOSU:1v3ytM:bSVwwzzObqLL6nU9UH8khvLLyuwdhxUBBXOaXSZRV-c", "expire_date": "2025-10-15T15:37:20.614Z"}}, {"model": "sessions.session", "pk": "ok9ldpddqob36lm39qcsoxw3qc0kkxip", "fields": {"session_data": ".eJxVjDsOwjAQBe_iGll2PnZMSc8Zot19Ng4gW8qnQtwdIqWA9s3Me6mRtjWP2xLncYI6K6tOvxuTPGLZAe5UblVLLes8sd4VfdBFXyvi83K4fweZlvytUxMZgZBM0_ngQH3yxiUIhFrvbIeBRSzQBxhKcMENzNL6zjWM1qr3BxzQOSU:1vNmiZ:noYQ9_4sRyO9NUAT8lLuhdDRvGGXkkFSZnaMOLq49Zw", "expire_date": "2025-12-09T06:40:03.944Z"}}, {"model": "sessions.session", "pk": "oucfej4dh8loh3gcvxanqwlzwcki41y2", "fields": {"session_data": ".eJxVjDsOwjAQBe_iGll2PnZMSc8Zot19Ng4gW8qnQtwdIqWA9s3Me6mRtjWP2xLncYI6K6tOvxuTPGLZAe5UblVLLes8sd4VfdBFXyvi83K4fweZlvytUxMZgZBM0_ngQH3yxiUIhFrvbIeBRSzQBxhKcMENzNL6zjWM1qr3BxzQOSU:1vFUuT:Jm5smz6V9ZfpHHw3UaqRIh0Bf-be80q0HVO-JRX4nxQ", "expire_date": "2025-11-16T10:02:05.243Z"}}, {"model": "sessions.session", "pk": "rco5f51lyj68k5uzoqcm4yg9ginvvl5n", "fields": {"session_data": ".eJxVjDsOwjAQBe_iGll2PnZMSc8Zot19Ng4gW8qnQtwdIqWA9s3Me6mRtjWP2xLncYI6K6tOvxuTPGLZAe5UblVLLes8sd4VfdBFXyvi83K4fweZlvytUxMZgZBM0_ngQH3yxiUIhFrvbIeBRSzQBxhKcMENzNL6zjWM1qr3BxzQOSU:1vMg9T:frchq4vr0xz0uc9-Lqe5TZBEykPO1jTVApl6F0kG3YM", "expire_date": "2025-12-06T05:27:15.932Z"}}, {"model": "sessions.session", "pk": "zdufp2knoj0w4zir7epc4j7jx5k9jdgg", "fields": {"session_data": ".eJxVjssOgyAURP-FdUN8grjs3m8g9zKgtkYSwFXTf29NXLTbOWcm8xKWjrLYI_tkV4hR1OL2mzG5p99PgAftc5Qu7iWtLE9FXjTLKcJv98v9G1goL992aDzDEELVdNooUB90pQIcHLVa1R0Gdq4GeoOKApRRA7NrdacaRnu-KnGeN2_zCs-UxFjS4d8fXn1BSg:1vMPSt:NARCoUNsvHONm9Cftr8NK2D3T63_QyjcEl6RD9MoYLw", "expire_date": "2025-12-05T11:38:11.895Z"}}, {"model": "courses.course", "pk": 1, "fields": {"title": "Python", "slug": "python", "created": "2025-10-01T15:45:16.508Z", "content": "python course", "owner": 1}}, {"model": "courses.module", "pk": 1, "fields": {"course": 1, "title": "Основы Django", "slug": "osnovy-django", "created": "2025-11-12T13:21:18.840Z", "note": "Шаги: установка Python, создание виртуального окружения, запуск django-admin startproject.", "order": 1}}, {"model": "courses.module", "pk": 2, "fields": {"course": 1, "title": "Первое приложение", "slug": "pervoe-prilozhenie", "created": "2025-11-12T13:21:31.182Z", "note": "2q2312", "order": 2}}, {"model": "courses.module", "pk": 3, "fields": {"course": 1, "title": "Шаблоны и контекст", "slug": "shablony-i-kontekst", "created": "2025-11-12T13:21:43.598Z", "note": "Шаблоны и контекст12123", "order": 3}}, {"model": "courses.lesson", "pk": 1, "fields": {"module": 1, "title": "Введение в Python", "slug": "vvedenie-v-python", "content": "### Responsive containersResponsive containers\r\n\r\nResponsive containers allow you to specify a class that is 100% wide until the specified breakpoint is reached, after which we apply max-widths for each of the higher breakpoints. For example, .container-sm is 100% wide to start until the sm breakpoint is reached, where it will scale up with md, lg, xl, and xxl.\r\n\r\n```html\r\n<div class=\"container-sm\">100% wide until small breakpoint</div>\r\n\r\n<div class=\"container-md\">100% wide until medium breakpoint</div>\r\n\r\n<div class=\"container-lg\">100% wide until large breakpoint</div>\r\n\r\n<div class=\"container-xl\">100% wide until extra large breakpoint</div>\r\n\r\n<div class=\"container-xxl\">100% wide until extra extra large breakpoint</div>\r\n```\r\n\r\n## Fluid containers\r\nUse .container-fluid for a full width container, spanning the entire width of the viewport.\r\n\r\n```html\r\n<div class=\"container-fluid\">\r\n  ...\r\n</div>\r\n```\r\n\r\n#### Sass variables \r\nAs shown above, Bootstrap generates a series of predefined container classes to help you build the layouts you desire. You may customize these predefined container classes by modifying the Sass map (found in _variables.scss) that powers them:\r\n\r\n`scss/_variables.scss`\r\n\r\n```\r\n$container-max-widths: (\r\n  sm: 540px,\r\n  md: 720px,\r\n  lg: 960px,\r\n  xl: 1140px,\r\n  xxl: 1320px\r\n);\r\n```\r\n\r\nFor more information and examples on how to modify our Sass maps and variables, please refer to the Sass section of the Grid documentation.\r\n\r\n## Sass mixins\r\nIn addition to customizing the Sass, you can also create your own containers with our Sass mixin.\r\n\r\n```html\r\n// Source mixin\r\n@mixin make-container($padding-x: $container-padding-x) {\r\n  width: 100%;\r\n  padding-right: $padding-x;\r\n  padding-left: $padding-x;\r\n  margin-right: auto;\r\n  margin-left: auto;\r\n}\r\n\r\n// Usage\r\n.custom-container {\r\n  @include make-container();\r\n}\r\n```", "created": "2025-11-12T13:46:28.492Z", "order": 1}}, {"model": "courses.lesson", "pk": 2, "fields": {"module": 1, "title": "Переменные и типы данных", "slug": "peremennye-i-tipy-dannyh", "content": "# Введение в Python\r\n\r\nPython — это высокоуровневый язык программирования с динамической типизацией. Он прост в изучении и широко используется для веб-разработки, анализа данных, автоматизации и машинного обучения.\r\n\r\n### Установка Python\r\n\r\nСкачайте Python с официального сайта и установите интерпретатор. Проверьте установку через команду в терминале:\r\n\r\n```bash\r\npython --version\r\n```\r\n\r\nПервая программа\r\n\r\nНапишите классическую программу \"Hello, World!\":\r\n\r\n```python\r\nprint(\"Hello, World!\")\r\n```\r\n\r\n#### Переменные и типы данных\r\n\r\nВ Python есть разные типы данных: целые числа, вещественные числа, строки и булевы значения. Переменные создаются присвоением значения:\r\n```python\r\nx = 10         # целое число\r\ny = 3.14       # вещественное число\r\nname = \"Alice\" # строка\r\nis_active = True # булево значение\r\n```\r\n\r\nУсловные конструкции\r\n\r\n```python\r\nage = 18\r\nif age >= 18:\r\n    print(\"Взрослый\")\r\nelse:\r\n    print(\"Несовершеннолетний\")\r\n```\r\n\r\n### Циклы\r\n\r\n```python\r\n# Цикл for\r\nfor i in range(5):\r\n    print(i)\r\n\r\n# Цикл while\r\ncount = 0\r\nwhile count < 5:\r\n    print(count)\r\n    count += 1\r\n```\r\n\r\nФункции\r\n\r\n```python\r\ndef greet(name):\r\n    return f\"Hello, {name}!\"\r\n\r\nprint(greet(\"Alice\"))\r\n```\r\n\r\nСписки и словари\r\n\r\n```python\r\nfruits = [\"apple\", \"banana\", \"cherry\"]\r\nperson = {\"name\": \"Alice\", \"age\": 25}\r\n```\r\n\r\nМодули\r\n\r\n```python\r\nimport math\r\nprint(math.sqrt(16))  # 4.0\r\n```\r\n\r\n**Заключение\r\n**\r\n*Python прост и гибок. Изучение базовых конструкций позволяет создавать программы и готовит к изучению ООП, работе с файлами, обработке исключений и использованию библиотек для анализа данных и веб-разработки.\r\n*", "created": "2025-11-12T13:46:37.673Z", "order": 2}}, {"model": "courses.lesson", "pk": 3, "fields": {"module": 1, "title": "Добавление и удаление столбцов в таблице", "slug": "slug-skug", "content": "Представьте, что вы проектируете базу данных для университета. Сначала таблица студентов включает всего два поля: ID и имя. Всё просто, студенты начинают пользоваться системой. Но спустя месяц к вам приходят преподаватели и говорят: \"А можно ещё добавить возраст?\", а чуть позже: \"Нужен ещё email\". Ну а затем: \"А давайте уберём, наконец, поле `middle_name`, всё равно его никто не заполняет!\". Вот тут-то вам и пригодятся навыки работы с `ALTER TABLE` для добавления и удаления столбцов.\r\n\r\n### Синтаксис добавления столбцовСинтаксис добавления столбцов\r\n\r\nИтак, чтобы добавить новый столбец в существующую таблицу PostgreSQL, используется команда `ALTER TABLE`. Смотрим на синтаксис:\r\n\r\n```SQL\r\nALTER TABLE table_name\r\nADD COLUMN column_name data_type [constraints];\r\n```\r\n\r\n- `table_name` — имя таблицы, в которую вы хотите добавить новый столбец.\r\n- `column_name` — имя столбца, который вы хотите добавить.\r\n- `data_type` — тип данных, например, VARCHAR, INTEGER или DATE.\r\n- `constraints` (необязательный параметр) — ограничения, которые вы хотите наложить на этот столбец, например, NOT NULL, DEFAULT и т.д.\r\n\r\n### Пример: добавляем новый столбец\r\nДопустим, у нас есть таблица `students`, которая была создана ранее:\r\n```SQL\r\nCREATE TABLE students (\r\n    id SERIAL PRIMARY KEY,\r\n    name VARCHAR(100) NOT NULL\r\n);\r\n```\r\n\r\nВдруг поступила задача добавить столбец `age` для хранения возраста студентов. Вот как это делается:\r\n\r\n```SQL\r\nALTER TABLE students\r\nADD COLUMN age INTEGER;\r\nТеперь структура таблицы students станет такой:\r\n```\r\n\r\nОсобенность: порядок выполнения изменений.\r\nИногда добавление столбцов с ограничениями может требовать знаний о порядке выполнения операций. Например, если вы добавляете столбец с NOT NULL, то сначала нужно заполнить его значениями по умолчанию, иначе PostgreSQL выдаст ошибку.", "created": "2025-11-12T13:46:46.459Z", "order": 6}}, {"model": "courses.lesson", "pk": 4, "fields": {"module": 1, "title": "Функции и аргументы", "slug": "funkcii-i-argumenty", "content": "## 🎓 Урок: Архитектура и Разработка Мультифункциональной Web-платформы на Django\r\n\r\n#### Цель\r\n\r\nЦель данной лекции — показать, как спроектировать платформу (LMS + CMD), используя современные практики, чтобы максимально продемонстрировать свои навыки работодателю (понимание масштабирования, асинхронности и безопасности транзакций).\r\n\r\n<div class=\"max-w-sm mx-auto bg-white shadow-md rounded-2xl p-6 border border-gray-100\">\r\n  <h2 class=\"text-xl font-semibold text-gray-900 mb-2\">Заголовок карточки</h2>\r\n  <p class=\"text-gray-600 text-sm leading-relaxed\">\r\n    Это простой пример карточки, оформленной с помощью Tailwind CSS. \r\n    Здесь может быть описание, текст урока или любой другой контент.\r\n  </p>\r\n</div>\r\n\r\n\r\n---\r\n\r\n### I. Архитектурный базис: Decoupled Approach 🧩\r\n\r\nДля создания современного, отзывчивого интерфейса и демонстрации полного цикла разработки мы используем **разделенную архитектуру (Decoupled Architecture)**.\r\n\r\n> Главная идея: Ваш Backend (Django) становится чистым API, а Frontend (React/Vue) — интерфейсом, который потребляет данные через HTTP-запросы.\r\n\r\n| Компонент | Назначение | Ключевой инструмент |\r\n| :--- | :--- | :--- |\r\n| **Backend** | Бизнес-логика, Безопасность, Доступ к БД. | **Django, Django REST Framework (DRF)** |\r\n| **Frontend** | Динамический UI, Визуализация данных (графики, календари). | **React / Vue / Next.js** |\r\n| **API** | Связующее звено. | **RESTful API** (JSON-формат) |\r\n\r\n---\r\n\r\n## II. Модуль управления доступом и безопасностью 🛡️\r\n\r\nЭтот раздел демонстрирует ваше понимание критически важной бизнес-логики и надежности.\r\n\r\n### 1. Реализация подписки и контроля доступа\r\n\r\n* **Модель `UserSubscription`:** Основной источник истины. Содержит поля `start_date` и `end_date`.\r\n* **Проверка доступа (Authorization):** Создание **декоратора** (`@subscription_required`) для автоматической проверки статуса перед обработкой запроса к любому курсу. Это инкапсулирует бизнес-логику.\r\n\r\n### 2. Финансовая надежность (Атомарность)\r\n\r\nПри обработке Webhooks от платежных систем (например, после успешной оплаты) нужно обеспечить целостность данных.\r\n\r\n> **Атомарная транзакция:** Либо все шаги транзакции (запись в историю платежей, активация подписки) выполняются, либо не выполняется ни один из них.\r\n\r\n**Инструмент:** Используйте контекстный менеджер `django.db.transaction.atomic()`:\r\n\r\n```python\r\nfrom django.db import transaction\r\n```\r\n\r\n# Гарантируем, что статус подписки не изменится, пока не будет создана запись о платеже\r\n```python\r\nwith transaction.atomic():\r\n    # 1. Создание записи о платеже\r\n    PaymentHistory.objects.create(...)\r\n    # 2. Активация подписки\r\n    user_sub.activate() \r\n    # Если на этом этапе произойдет сбой, обе записи будут отменены (Rollback)```", "created": "2025-11-12T13:46:56.261Z", "order": 4}}, {"model": "courses.lesson", "pk": 5, "fields": {"module": 2, "title": "Вторая норм лекция", "slug": "vtoraya-norm-lekciya", "content": "## Лекция: Основы языка программирования Python\r\n**Python** — это высокоуровневый, интерпретируемый язык программирования общего назначения с динамической типизацией. Он известен своим чистым и легко читаемым синтаксисом, что делает его отличным выбором как для новичков, так и для опытных разработчиков.\r\n\r\n### 1. Переменные и типы данных\r\n\r\nВ Python не нужно заранее объявлять тип переменной. Тип определяется автоматически при \r\nприсваивании значения.\r\n\r\n**Основные типы данных:**\r\n`int`: Целые числа (10, -5)\r\n`float`: Числа с плавающей точкой (3.14, 0.001)\r\n`str`: Строки (текст в одинарных или двойных кавычках: `'hello'`, `\"мир\"`)\r\n`bool`: Логический тип (`True` или `False`)\r\n`list`: Списки (упорядоченные коллекции элементов: `[1, 2, 'a']`)\r\n`dict`: Словари (неупорядоченные коллекции пар ключ-значение: `{'key': 'value'}`)\r\n\r\n**Пример создания переменных**\r\n\r\n```python\r\n# main.py\r\n\r\nname = \"Алиса\"\r\nage = 25\r\nheight = 1.75\r\nis_student = True\r\n```\r\n\r\n### 2. Условные операторы (if/elif/else)\r\n\r\nУправление ходом выполнения программы осуществляется с помощью условных операторов. Обратите внимание на использование отступов (4 пробела или Tab) для обозначения блоков кода — это критически важно в Python.\r\n\r\n```python\r\ntemperature = 20\r\n\r\nif temperature > 30:\r\n    print(\"Очень жарко!\")\r\nelif temperature > 15:\r\n    print(\"Тепло.\")\r\nelse:\r\n    print(\"Прохладно.\")\r\n```", "created": "2025-11-21T14:44:11.874Z", "order": 5}}, {"model": "courses.lessonprogress", "pk": 1, "fields": {"student": 1, "lesson": 4, "is_complete": true, "complete_at": "2025-11-21T14:28:30.614Z"}}, {"model": "courses.lessonprogress", "pk": 2, "fields": {"student": 1, "lesson": 3, "is_complete": true, "complete_at": "2025-11-21T14:28:33.409Z"}}, {"model": "courses.lessonprogress", "pk": 3, "fields": {"student": 1, "lesson": 4, "is_complete": true, "complete_at": "2025-11-21T14:36:25.977Z"}}, {"model": "courses.lessonprogress", "pk": 4, "fields": {"student": 1, "lesson": 4, "is_complete": true, "complete_at": "2025-11-21T14:36:29.780Z"}}, {"model": "courses.lessonprogress", "pk": 5, "fields": {"student": 1, "lesson": 5, "is_complete": true, "complete_at": "2025-11-21T14:46:20.893Z"}}, {"model": "courses.lessonprogress", "pk": 6, "fields": {"student": 1, "lesson": 4, "is_complete": true, "complete_at": "2025-11-22T06:01:51.855Z"}}]